smrt/__init__.py
smrt/atmosphere/__init__.py
smrt/atmosphere/pyrtlib_atmosphere.py
smrt/atmosphere/pyrtlib_climatology_atmosphere.py
smrt/atmosphere/pyrtlib_era5_atmosphere.py
smrt/atmosphere/simple_atmosphere.py
smrt/atmosphere/simple_isotropic_atmosphere.py
smrt/atmosphere/test_atmosphere.py
smrt/core/__init__.py
smrt/core/atmosphere.py
smrt/core/error.py
smrt/core/fresnel.py
smrt/core/globalconstants.py
smrt/core/interface.py
smrt/core/layer.py
smrt/core/lib.py
smrt/core/model.py
smrt/core/optional_numba.py
smrt/core/plugin.py
smrt/core/result.py
smrt/core/run_promise.py
smrt/core/sensitivity_study.py
smrt/core/sensor.py
smrt/core/snowpack.py
smrt/core/test_globalconstants.py
smrt/core/test_interface.py
smrt/core/test_layer.py
smrt/core/test_lib.py
smrt/core/test_result.py
smrt/core/test_sensor.py
smrt/core/test_snowpack.py
smrt/core/vector3.py
smrt/emmodel/__init__.py
smrt/emmodel/common.py
smrt/emmodel/commontest.py
smrt/emmodel/dmrt_qca_shortrange.py
smrt/emmodel/dmrt_qcacp_shortrange.py
smrt/emmodel/iba.py
smrt/emmodel/iba_maxwell_garnett.py
smrt/emmodel/iba_original.py
smrt/emmodel/nonscattering.py
smrt/emmodel/prescribed_kskaeps.py
smrt/emmodel/rayleigh.py
smrt/emmodel/sce_common.py
smrt/emmodel/sce_rechtsman08.py
smrt/emmodel/sce_torquato21.py
smrt/emmodel/sce_torquato21_shortrange.py
smrt/emmodel/sft_rayleigh.py
smrt/emmodel/symsce_torquato21.py
smrt/emmodel/symsce_torquato21_shortrange.py
smrt/emmodel/test_iba.py
smrt/emmodel/test_iba_original.py
smrt/emmodel/test_prescribed_kskaeps.py
smrt/emmodel/test_rayleigh.py
smrt/emmodel/test_sft_rayleigh.py
smrt/emmodel/test_symsce_torquato21.py
smrt/inputs/__init__.py
smrt/inputs/altimeter_list.py
smrt/inputs/make_medium.py
smrt/inputs/make_soil.py
smrt/inputs/sensor_list.py
smrt/inputs/test_make_medium.py
smrt/inputs/test_sensor_list.py
smrt/interface/__init__.py
smrt/interface/coherent_flat.py
smrt/interface/flat.py
smrt/interface/geometrical_optics.py
smrt/interface/geometrical_optics_backscatter.py
smrt-1.5.1.dist-info/licenses/LICENSE
smrt-1.5.1.dist-info/METADATA
smrt-1.5.1.dist-info/WHEEL
smrt-1.5.1.dist-info/top_level.txt
smrt-1.5.1.dist-info/RECORD
