Metadata-Version: 2.4
Name: smrt
Version: 1.5.1
Summary: The Snow Microwave Radiative Transfer (SMRT) model is a highly modular model to compute the thermal emission and backscattering coefficient of snowpacks and other cryospheric bodies in the microwave domain.
Author-email: Ghislain Picard <ghislain.picard@univ-grenoble-alpes.fr>, Melody Sandells <melody.sandells@gmail.com>, Henning Löwe <loewe@slf.ch>
License: DISCLAIMER: This version of SMRT is an early release. As such, some components may not be fully implemented or may give rise to unexpected behaviour. Please use this software with caution, ask for assistance if needed, and let us know any feedback you may have.
Project-URL: Homepage, https://http://smrt-model.science/l
Project-URL: Issues, https://github.com/smrt/smrt-model/issues
Project-URL: Documentation, http://smrt.readthedocs.io/
Project-URL: Repository, https://github.com/smrt-model/smrt.git
Classifier: Development Status :: 5 - Production/Stable
Classifier: Intended Audience :: Science/Research
Classifier: Topic :: Scientific/Engineering
Requires-Python: >=3.9
License-File: LICENSE
Requires-Dist: numpy>=1.15
Requires-Dist: pandas>=0.20.3
Requires-Dist: scipy>=1.0.0
Requires-Dist: xarray>=0.10.3
Requires-Dist: numba>=0.53
Requires-Dist: joblib>=1.0.0
Provides-Extra: progressbar
Requires-Dist: tqdm; extra == "progressbar"
Provides-Extra: pyrtlib
Requires-Dist: scikit-learn; extra == "pyrtlib"
Requires-Dist: bs4; extra == "pyrtlib"
Requires-Dist: netCDF4; extra == "pyrtlib"
Requires-Dist: requests; extra == "pyrtlib"
Requires-Dist: cdsapi; extra == "pyrtlib"
Requires-Dist: cfgrib; extra == "pyrtlib"
Requires-Dist: pyrtlib; extra == "pyrtlib"
Provides-Extra: gsw
Requires-Dist: gsw; extra == "gsw"
Dynamic: license-file
